Workbook

Sheet Assumptions
A1: Assumptions — every input lives here
A2: Yellow cells are yours to edit. Every seeded number is a PLACEHOLDER, not a quote. Replace them as real numbers arrive and the whole model follows.
A4: PRICING (VAT-inclusive, as displayed)
A5: VAT rate | D5: 0.15 | F5: Saudi standard rate. Consumer prices must be displayed VAT-inclusive.
A6: Core pad — price cell 1 | D6: 39 | E6: SAR | F6: Also the founder preorder price
A7: Core pad — price cell 2 | D7: 49 | E7: SAR | F7: The premium test price
A8: Gift bundle — price cell 1 | D8: 79 | E8: SAR
A9: Gift bundle — price cell 2 | D9: 89 | E9: SAR
A11: PRODUCT COST — replace with printer quotes
A12: Print cost/unit @ 300 | D12: 18 | E12: SAR | F12: PLACEHOLDER — quote required
A13: Print cost/unit @ 500 | D13: 14 | E13: SAR | F13: PLACEHOLDER — quote required
A14: Print cost/unit @ 750 | D14: 12 | E14: SAR | F14: PLACEHOLDER — quote required
A15: Print cost/unit @ 1,000 | D15: 11 | E15: SAR | F15: PLACEHOLDER — quote required
A16: Print cost/unit @ 1,500 | D16: 9.5 | E16: SAR | F16: PLACEHOLDER — quote required
A17: Packaging: polybag, insert card, mailer | D17: 3.5 | E17: SAR | F17: Giftability sits here — do not cut it first
A18: Inbound handling and storage/unit | D18: 1 | E18: SAR
A19: Pick and pack labour/unit | D19: 2 | E19: SAR | F19: Your time is a cost even if you do not invoice it
A20: Gift bundle add-on cost (pencils, stickers) | D20: 9.5 | E20: SAR | F20: Adds SASO/SABER obligations — see compliance checklist
A22: FULFILMENT AND FEES
A23: Actual domestic shipping cost/order | D23: 22 | E23: SAR | F23: PLACEHOLDER — get courier quotes
A24: Shipping charged to customer | D24: 15 | E24: SAR | F24: Set to 0 to model free shipping; the subsidy is the difference
A25: Payment gateway % | D25: 0.025 | F25: mada/card. Confirm with your provider
A26: Payment gateway fixed fee/order | D26: 1 | E26: SAR
A27: Return / refund rate | D27: 0.04 | F27: Assume the product comes back unsaleable
A28: Store platform monthly fee | D28: 250 | E28: SAR | F28: Fixed cost — sits in Pilot P&L, not in unit contribution
A30: MARKETING AND TARGETS
A31: Cost per qualified click | D31: 1.6 | E31: SAR | F31: MEASURE THIS in the first 48 hours; do not assume it
A32: Contribution retained after CAC | D32: 0.3 | F32: 0% = break-even on acquisition. 30% keeps a margin for the pilot.
A34: The two numbers most likely to be wrong are the print quote and the shipping cost, and they are the two with the largest effect on whether this works. Get three quotes for each before you trust any output of this model.

Sheet COGS
A1: Cost of goods per unit, by print quantity
A2: Landed cost of one pad in a box, before shipping and payment fees. The print-run decision reads off this table.
A4: Print quantity | B4: Print/unit | C4: Packaging | D4: Handling | E4: Pick & pack | F4: COGS/unit | G4: Total product cost
A5: 300 | B5: =Assumptions!D12 | C5: =Assumptions!D17 | D5: =Assumptions!D18 | E5: =Assumptions!D19 | F5: =SUM(B5:E5) | G5: =B5*A5
A6: 500 | B6: =Assumptions!D13 | C6: =Assumptions!D17 | D6: =Assumptions!D18 | E6: =Assumptions!D19 | F6: =SUM(B6:E6) | G6: =B6*A6
A7: 750 | B7: =Assumptions!D14 | C7: =Assumptions!D17 | D7: =Assumptions!D18 | E7: =Assumptions!D19 | F7: =SUM(B7:E7) | G7: =B7*A7
A8: 1000 | B8: =Assumptions!D15 | C8: =Assumptions!D17 | D8: =Assumptions!D18 | E8: =Assumptions!D19 | F8: =SUM(B8:E8) | G8: =B8*A8
A9: 1500 | B9: =Assumptions!D16 | C9: =Assumptions!D17 | D9: =Assumptions!D18 | E9: =Assumptions!D19 | F9: =SUM(B9:E9) | G9: =B9*A9
A11: Gift bundle COGS (at 1,000 units) | F11: =F8+Assumptions!D20
A13: The unit price at 1,500 will always look better than at 500. That is the printer's cost curve, not your demand. Print to preorder evidence — unsold inventory is the most expensive way to buy a lower unit cost.
A15: Pick-and-pack labour is included deliberately. Founders routinely price at zero because they pack the boxes themselves, then discover the model never worked once anyone else had to be paid to do it.

Sheet Unit Economics
A1: Contribution per order
A2: VAT-inclusive prices, net revenue backed out at the standard rate. Contribution is what is left to pay for acquisition and everything fixed.
A4: Offer | B4: Price (inc VAT) | C4: VAT | D4: Net revenue | E4: COGS | F4: Shipping subsidy | G4: Payment fees | H4: Returns reserve | I4: CONTRIBUTION
A5: Core pad @ 39 | B5: =Assumptions!D6 | C5: =B5-B5/(1+Assumptions!D5) | D5: =B5/(1+Assumptions!D5) | E5: =COGS!F8 | F5: =MAX(0,Assumptions!D23-Assumptions!D24) | G5: =B5*Assumptions!D25+Assumptions!D26 | H5: =Assumptions!D27*(E5+Assumptions!D23) | I5: =D5-E5-F5-G5-H5
A6: Core pad @ 49 | B6: =Assumptions!D7 | C6: =B6-B6/(1+Assumptions!D5) | D6: =B6/(1+Assumptions!D5) | E6: =COGS!F8 | F6: =MAX(0,Assumptions!D23-Assumptions!D24) | G6: =B6*Assumptions!D25+Assumptions!D26 | H6: =Assumptions!D27*(E6+Assumptions!D23) | I6: =D6-E6-F6-G6-H6
A7: Gift bundle @ 79 | B7: =Assumptions!D8 | C7: =B7-B7/(1+Assumptions!D5) | D7: =B7/(1+Assumptions!D5) | E7: =COGS!F11 | F7: =MAX(0,Assumptions!D23-Assumptions!D24) | G7: =B7*Assumptions!D25+Assumptions!D26 | H7: =Assumptions!D27*(E7+Assumptions!D23) | I7: =D7-E7-F7-G7-H7
A8: Gift bundle @ 89 | B8: =Assumptions!D9 | C8: =B8-B8/(1+Assumptions!D5) | D8: =B8/(1+Assumptions!D5) | E8: =COGS!F11 | F8: =MAX(0,Assumptions!D23-Assumptions!D24) | G8: =B8*Assumptions!D25+Assumptions!D26 | H8: =Assumptions!D27*(E8+Assumptions!D23) | I8: =D8-E8-F8-G8-H8
A10: Contribution margin on net revenue | D10: =IFERROR(I5/D5,"") | E10: =IFERROR(I6/D6,"") | F10: =IFERROR(I7/D7,"") | G10: =IFERROR(I8/D8,"")
D11: pad@39 | E11: pad@49 | F11: bundle@79 | G11: bundle@89
A13: READ THIS BEFORE ANYTHING ELSE: at SAR 39 with a subsidised shipping charge, contribution is thin enough that almost nothing is left to pay for acquiring the customer. That is not a modelling artefact — it is the central economic problem of a single low-priced physical product shipped one at a time.
A15: Three levers, in order of how much they move the number: (1) charge shipping in full rather than subsidising it, (2) launch at 49 rather than 39, (3) move volume into the bundle. The paid test tells you what each one costs in conversion. Change the Assumptions tab and watch this table — that comparison IS the pricing decision.
A17: The founder preorder at SAR 39 is a deliberate loss-leader against a thin contribution: you are buying first reviews and operational proof, not margin. Budget it as marketing spend, cap the quantity, and do not let it become the launch price by default.

Sheet Break-even
A1: Maximum allowable CAC, and the conversion rate it demands
A2: This tab produces the Gate 4 threshold. Copy the required conversion rate into the sprint workbook's Paid Test tab BEFORE the paid test finishes.
A4: Offer | B4: Contribution | C4: Max CAC at break-even | D4: Max CAC at target retention | E4: Cost per click | F4: Required conversion rate | G4: Clicks per order | H4: Ad spend per order
A5: Core pad @ 39 | B5: ='Unit Economics'!I5 | C5: =B5 | D5: =B5*(1-Assumptions!D32) | E5: =Assumptions!D31 | F5: =IFERROR(E5/D5,"n/a") | G5: =IFERROR(D5/E5,"n/a") | H5: =D5
A6: Core pad @ 49 | B6: ='Unit Economics'!I6 | C6: =B6 | D6: =B6*(1-Assumptions!D32) | E6: =Assumptions!D31 | F6: =IFERROR(E6/D6,"n/a") | G6: =IFERROR(D6/E6,"n/a") | H6: =D6
A7: Gift bundle @ 79 | B7: ='Unit Economics'!I7 | C7: =B7 | D7: =B7*(1-Assumptions!D32) | E7: =Assumptions!D31 | F7: =IFERROR(E7/D7,"n/a") | G7: =IFERROR(D7/E7,"n/a") | H7: =D7
A8: Gift bundle @ 89 | B8: ='Unit Economics'!I8 | C8: =B8 | D8: =B8*(1-Assumptions!D32) | E8: =Assumptions!D31 | F8: =IFERROR(E8/D8,"n/a") | G8: =IFERROR(D8/E8,"n/a") | H8: =D8
A10: HOW TO READ COLUMN F: it is the landing-page conversion rate you must achieve for the offer to pay for its own advertising. If it reads 8%, you need 8 preorders per 100 qualified clicks — and typical cold-traffic conversion on a new brand's product page is low single digits. A required rate far above that is the model telling you the offer cannot carry paid acquisition at that price.
A12: If the required rate is out of reach at every price point, paid acquisition is not your channel at launch, and the answer is not a bigger budget. It is organic and creator-led distribution, a higher basket, or a different product. Better to know that in September for the cost of a test than in December for the cost of a print run.
A14: GATE 5 — ECONOMICS
A15: Threshold: positive contribution after product, packaging, payment, shipping subsidy, returns AND test CAC.
A16: Actual CAC observed in the paid test (enter): | D16: 25
A17: Contribution after CAC, by offer:
A18: pad@39 | C18: pad@49 | E18: bundle@79 | G18: bundle@89
A19: =B5-$D$16 | C19: =B6-$D$16 | E19: =B7-$D$16 | G19: =B8-$D$16
A21: =IF(MAX(B5:B8)-D16>0,"GATE 5: PASSES on at least one offer — launch at the offer with the highest contribution per visitor","GATE 5: FAILS at every price point — DO NOT PRINT")
A23: THE STOP RULE: if contribution after CAC is negative at both 39 and 49 including the bundle, stop. This is the one gate no copy, photography or message can fix, because it is arithmetic — volume multiplies a negative number. Stopping here leaves the SAR 6,500 print line unspent and you keep the language bank, the prototype, the cultural review and a working store.

Sheet Pilot P&L
A1: Pilot P&L — three demand scenarios
A2: Against a 500-unit print run at the SAR 49 core price. Change the unit numbers to match your actual preorder evidence before the print decision.
A4: Line | B4: Pessimistic | C4: Base | D4: Optimistic | E4: Note
A5: Units sold (of a 500 print run) | B5: 120 | C5: 250 | D5: 420 | E5: The pessimistic case is the one to plan cash against
A6: — of which gift bundle | B6: =ROUND(B5*0.2,0) | C6: =ROUND(C5*0.2,0) | D6: =ROUND(D5*0.2,0) | E6: Assumed 20% bundle mix
A7: Net revenue | B7: =(B5-B6)*'Unit Economics'!D6+B6*'Unit Economics'!D7 | C7: =(C5-C6)*'Unit Economics'!D6+C6*'Unit Economics'!D7 | D7: =(D5-D6)*'Unit Economics'!D6+D6*'Unit Economics'!D7 | E7: VAT excluded
A8: Contribution before fixed costs | B8: =(B5-B6)*'Unit Economics'!I6+B6*'Unit Economics'!I7 | C8: =(C5-C6)*'Unit Economics'!I6+C6*'Unit Economics'!I7 | D8: =(D5-D6)*'Unit Economics'!I6+D6*'Unit Economics'!I7 | E8: From the Unit Economics tab
A9: Ad spend | B9: 2500 | C9: 2500 | D9: 2500 | E9: The budgeted paid test and launch line
A10: Platform fees (3 months) | B10: =Assumptions!D28*3 | C10: =Assumptions!D28*3 | D10: =Assumptions!D28*3 | E10: Store subscription
A11: Print run cost (500 units) | B11: =COGS!G6 | C11: =COGS!G6 | D11: =COGS!G6 | E11: Paid up front, whether or not it sells
A12: Validation + cultural review + prototype | B12: 8500 | C12: 8500 | D12: 8500 | E12: Spent before any revenue
A13: Store, content, contingency | B13: 4500 | C13: 4500 | D13: 4500
A14: PILOT RESULT | B14: =B8-B9-B10-B11-B12-B13 | C14: =C8-C9-C10-C11-C12-C13 | D14: =D8-D9-D10-D11-D12-D13 | E14: Cash position at the end of the pilot
A15: Unsold inventory (units) | B15: =500-B5 | C15: =500-C5 | D15: =500-D5 | E15: Not a loss yet — but it is cash you cannot spend
A17: The print run cost sits BELOW the contribution line on purpose: it is spent before the first sale and it does not come back. That is why the pilot result can be negative even when every unit sold made money — and why the print quantity is the most consequential number on this page.
A19: 'Unsold inventory' is not a loss on the day the pilot ends — the pads keep. But it is cash you cannot spend on the next decision, and the brief's guidance is explicit: smaller first run, replenish only on evidence.
A21: Fixed costs here total roughly SAR 15,500 before a single pad ships. Against a pilot ceiling of SAR 25,000 that is the real constraint on print quantity — not the printer's minimum order.

Sheet Budget Tracker
A1: SAR 22,000 pilot budget — plan vs actual
A2: The working allocation from the decision brief. Update Actual as you spend; variance and remaining budget compute themselves.
A4: Use of funds | B4: Planned SAR | C4: Actual SAR | D4: Variance | E4: % of budget | F4: Purpose
A5: Parent/child validation | B5: 2500 | D5: =IF(C5="","",C5-B5) | E5: =B5/$B$12 | F5: Recruiting, incentives, survey and prototype sessions
A6: Arabic/cultural/editorial review | B6: 2500 | D6: =IF(C6="","",C6-B6) | E6: =B6/$B$12 | F6: Accuracy, tone, bilingual copy and claims review
A7: Prototype refinement & samples | B7: 3500 | D7: =IF(C7="","",C7-B7) | E7: =B7/$B$12 | F7: Print tests, paper/binding trials, child-use iteration
A8: Initial local production | B8: 6500 | D8: =IF(C8="","",C8-B8) | E8: =B8/$B$12 | F8: Pilot print run; quantity set AFTER the gate review
A9: Store & launch content | B9: 3000 | D9: =IF(C9="","",C9-B9) | E9: =B9/$B$12 | F9: Product page, photography/video, customer-support setup
A10: Paid message/price tests | B10: 2500 | D10: =IF(C10="","",C10-B10) | E10: =B10/$B$12 | F10: Targeted traffic before and during preorder
A11: Contingency & operating fees | B11: 1500 | D11: =IF(C11="","",C11-B11) | E11: =B11/$B$12 | F11: Shipping tests, corrections, packaging, platform variance
A12: TOTAL | B12: =SUM(B5:B11) | C12: =SUM(C5:C11) | D12: =IF(C12=0,"",C12-B12)
A14: Pilot ceiling | B14: 25000
A15: Headroom against ceiling | B15: =B14-B12
A16: Spent before the gate review (lines 1-3 + tests) | B16: =B5+B6+B7+B10
A17: At risk only if you print (lines 4-5 + contingency) | B17: =B8+B9+B11
A19: Rows 16 and 17 are the shape of the whole plan: roughly SAR 11,000 buys you the evidence, and the remaining SAR 11,000 is only committed once the evidence says go. Keeping that split intact is what makes stopping at the gate review survivable rather than catastrophic.
A21: This is a working budget, not supplier quotations. Do not place the full production order until prototype, cultural review and preorder evidence meet the decision gates.
