Workbook

Sheet SKUs
A1: The range — contribution by SKU
A2: VAT-inclusive prices. Costs are PLACEHOLDERS pending quotes; the flagship figures match 03-economics. 'Attach' SKUs ride an existing parcel, which is why their thin margin still beats a price rise.
A4: SKU | B4: Price inc VAT | C4: Net revenue | D4: Unit cost | E4: Shipping subsidy | F4: Payment fee | G4: Returns | H4: CONTRIBUTION | I4: Role
A5: Sticker sheets | B5: 17 | C5: =B5/1.15 | D5: 3 | E5: 0 | F5: =IF(E5=0,0,B5*0.025+1) | G5: =0.04*(D5+IF(E5=0,0,22)) | H5: =C5-D5-E5-F5-G5 | I5: Attach only. No extra shipping, artwork already paid for.
A6: Postcard set | B6: 27 | C6: =B6/1.15 | D6: 7 | E6: 7 | F6: =IF(E6=0,0,B6*0.025+1) | G6: =0.04*(D6+IF(E6=0,0,22)) | H6: =C6-D6-E6-F6-G6 | I6: Entry price and a gifting occasion.
A7: Core pad (39) | B7: 39 | C7: =B7/1.15 | D7: 17.5 | E7: 7 | F7: =IF(E7=0,0,B7*0.025+1) | G7: =0.04*(D7+IF(E7=0,0,22)) | H7: =C7-D7-E7-F7-G7 | I7: The proposition at the low test price.
A8: Core pad (49) | B8: 49 | C8: =B8/1.15 | D8: 17.5 | E8: 7 | F8: =IF(E8=0,0,B8*0.025+1) | G8: =0.04*(D8+IF(E8=0,0,22)) | H8: =C8-D8-E8-F8-G8 | I8: The proposition at the premium test price.
A9: Ages 3-5 edition | B9: 37 | C9: =B9/1.15 | D9: 17.5 | E9: 7 | F9: =IF(E9=0,0,B9*0.025+1) | G9: =0.04*(D9+IF(E9=0,0,22)) | H9: =C9-D9-E9-F9-G9 | I9: Unlocks the younger sibling.
A10: Ages 9-12 edition | B10: 47 | C10: =B10/1.15 | D10: 18.5 | E10: 7 | F10: =IF(E10=0,0,B10*0.025+1) | G10: =0.04*(D10+IF(E10=0,0,22)) | H10: =C10-D10-E10-F10-G10 | I10: Answers 'my older child called it babyish'.
A11: Gift bundle | B11: 89 | C11: =B11/1.15 | D11: 27 | E11: 7 | F11: =IF(E11=0,0,B11*0.025+1) | G11: =0.04*(D11+IF(E11=0,0,22)) | H11: =C11-D11-E11-F11-G11 | I11: Pad + stickers + pencils.
A12: Activity kit | B12: 149 | C12: =B12/1.15 | D12: 55 | E12: 7 | F12: =IF(E12=0,0,B12*0.025+1) | G12: =0.04*(D12+IF(E12=0,0,22)) | H12: =C12-D12-E12-F12-G12 | I12: The only SKU whose contribution carries a real CAC.
A14: Sticker sheets carry no shipping subsidy and no payment fee because they attach to an order that already pays both. That is the whole argument for launching them first: the cheapest possible test of whether a customer will buy twice, on artwork already paid for.
A16: The activity kit is the only line whose contribution can absorb a realistic acquisition cost. If paid advertising is ever going to work for this business, it works on this SKU and not on the pad. It is also the SKU blocked on SASO/SABER conformity for the pencils.

Sheet Attach
A1: Attach rate vs. a price rise
A2: Two ways to raise contribution per order. One costs conversion; the other does not.
A4: Lever | B4: Change | C4: Contribution/order | D4: vs baseline | E4: Conversion cost | F4: Verdict
A5: Baseline: core pad @ 39 | B5: — | C5: ='SKUs'!H7 | E5: — | F5: The problem case
A6: Raise price to 49 | B6: +SAR 10 | C6: ='SKUs'!H8 | D6: =C6-C5 | E6: Real — this is what the price cell measures | F6: Worth testing, costs conversion
A7: Attach stickers to 30% of orders | B7: +30% x sticker contribution | C7: =C5+0.3*'SKUs'!H5 | D7: =C7-C5 | E7: None — same parcel, same checkout | F7: Free contribution. Do this first.
A8: Attach stickers to 50% of orders | B8: +50% x sticker contribution | C8: =C5+0.5*'SKUs'!H5 | D8: =C8-C5 | E8: None | F8: Needs the offer designed into the page
A9: Charge shipping in full | B9: 15 -> 22 | C9: =C5+7 | D9: =C9-C5 | E9: Real, and untested | F9: Largest single controllable leak
A10: Move the order to the bundle | B10: 39 -> 89 | C10: ='SKUs'!H11 | D10: =C10-C5 | E10: Real — a much bigger ask | F10: The offer paid ads could afford
A12: Read rows 7 and 6 against each other. Attaching stickers to 30% of orders adds contribution with ZERO conversion cost, because the customer has already decided to buy and the parcel is already being shipped. A price rise adds more per order and costs conversion on every order. Do the free one first, then test the priced one.
A14: This is why the range is sequenced stickers-first rather than second-title-first. The cheapest contribution in the business is the SKU that rides an order you already won.

Sheet Cohort
A1: 100 customers, 12 months
A2: What a cohort is worth once there is more than one thing to buy. Edit the yellow assumptions; everything else follows.
A4: ASSUMPTIONS
A5: Cohort size | C5: 100 | D5: customers acquired in month 0
A6: Repeat rate within 12 months | C6: 0.25 | D6: the number that decides the business
A7: Second purchases per repeater | C7: 1.4 | D7: some buy twice more
A8: Sticker attach rate | C8: 0.3 | D8: share of orders adding stickers
A9: Blended CAC actually paid | C9: 25 | D9: from the paid test
A11: COHORT VALUE
A12: First orders | B12: =C5
A13: First-order contribution (core pad @ 49) | B13: =B12*'SKUs'!H8
A14: Sticker attach on first orders | B14: =B12*C8*'SKUs'!H5
A15: Repeat customers | B15: =C5*C6
A16: Repeat orders | B16: =B15*C7
A17: Repeat-order contribution | B17: =B16*'SKUs'!H8
A18: Sticker attach on repeat orders | B18: =B16*C8*'SKUs'!H5
A19: TOTAL 12-MONTH CONTRIBUTION | B19: =B13+B14+B17+B18
A20: Acquisition cost paid (first orders only) | B20: =B12*C9
A21: NET COHORT VALUE | B21: =B19-B20
A22: Contribution per acquired customer | B22: =B19/C5
A23: Effective CAC headroom per customer | B23: =B19/C5
A25: The last row is the point. First-order economics say you can afford roughly SAR 14 of CAC on a core pad. Cohort economics — with a 25% repeat rate and a 30% sticker attach — say you can afford considerably more, because the second order carries no acquisition cost at all. That difference is the entire argument for building a range.
A27: Do not spend against cohort economics until you have MEASURED the repeat rate. Spending a projected lifetime value you have not yet observed is the most common way a small physical-product business runs out of cash while its spreadsheet looks healthy.

Sheet Repeat Sensitivity
A1: CAC headroom as repeat rate varies
A2: The decisive table. Read down the column that matches your observed repeat rate — not the one you hope for.
A4: Repeat rate | B4: Repeat orders per 100 | C4: Total contribution | D4: Per acquired customer | E4: Max CAC at 30% retained | F4: Verdict
A5: 0 | B5: =100*A5*Cohort!$C$7 | C5: =(100+B5)*'SKUs'!$H$8+(100+B5)*Cohort!$C$8*'SKUs'!$H$5 | D5: =C5/100 | E5: =D5*0.7 | F5: Single-transaction business. Gift positioning, accept the CAC.
A6: 0.05 | B6: =100*A6*Cohort!$C$7 | C6: =(100+B6)*'SKUs'!$H$8+(100+B6)*Cohort!$C$8*'SKUs'!$H$5 | D6: =C6/100 | E6: =D6*0.7 | F6: Single-transaction business. Gift positioning, accept the CAC.
A7: 0.1 | B7: =100*A7*Cohort!$C$7 | C7: =(100+B7)*'SKUs'!$H$8+(100+B7)*Cohort!$C$8*'SKUs'!$H$5 | D7: =C7/100 | E7: =D7*0.7 | F7: Marginal. Paid acquisition still will not work.
A8: 0.15 | B8: =100*A8*Cohort!$C$7 | C8: =(100+B8)*'SKUs'!$H$8+(100+B8)*Cohort!$C$8*'SKUs'!$H$5 | D8: =C8/100 | E8: =D8*0.7 | F8: Marginal. Paid acquisition still will not work.
A9: 0.2 | B9: =100*A9*Cohort!$C$7 | C9: =(100+B9)*'SKUs'!$H$8+(100+B9)*Cohort!$C$8*'SKUs'!$H$5 | D9: =C9/100 | E9: =D9*0.7 | F9: The range is working. Paid becomes arguable.
A10: 0.25 | B10: =100*A10*Cohort!$C$7 | C10: =(100+B10)*'SKUs'!$H$8+(100+B10)*Cohort!$C$8*'SKUs'!$H$5 | D10: =C10/100 | E10: =D10*0.7 | F10: The range is working. Paid becomes arguable.
A11: 0.3 | B11: =100*A11*Cohort!$C$7 | C11: =(100+B11)*'SKUs'!$H$8+(100+B11)*Cohort!$C$8*'SKUs'!$H$5 | D11: =C11/100 | E11: =D11*0.7 | F11: The range is working. Paid becomes arguable.
A12: 0.4 | B12: =100*A12*Cohort!$C$7 | C12: =(100+B12)*'SKUs'!$H$8+(100+B12)*Cohort!$C$8*'SKUs'!$H$5 | D12: =C12/100 | E12: =D12*0.7 | F12: Masterbrand thesis proved. Build the subscription.
A13: 0.5 | B13: =100*A13*Cohort!$C$7 | C13: =(100+B13)*'SKUs'!$H$8+(100+B13)*Cohort!$C$8*'SKUs'!$H$5 | D13: =C13/100 | E13: =D13*0.7 | F13: Masterbrand thesis proved. Build the subscription.
A15: Compare column E against the cost per acquisition you actually observe. At 0% repeat the business must be acquired one customer at a time forever, which the flagship economics say is not affordable. Every row down this table is the range doing its job.
A17: GATE FOR WAVE TWO: at least 20% of the flagship's buyers purchase the second title within 8 weeks, without a discount. Below that, stop extending the range and either fix the flagship or accept that this is a gifting business and price it accordingly.

Sheet Sequencing
A1: Waves and gates
A2: Nothing in a later wave is funded until the gate above it passes.
A4: When | B4: What | C4: Why now | D4: Gate before the next wave | E4: Blocked on
A5: Nov 2026 | B5: Flagship launch | C5: The proposition | D5: 20-order dry run passed; first reviews real | E5: —
A6: Jan 2027 | B6: Sticker sheets | C6: Cheapest repeat test; artwork already paid for | D6: Any repeat purchase at all | E6: Confirm stickers are not toy-classified
A7: Feb 2027 | B7: Postcards | C7: Entry price, gifting, a child mails the marketing | E7: —
A8: Feb 2027 | B8: Founding Day capsule | C8: Captures the spike without becoming an occasion brand | E8: Dated, limited, never restocked
A9: Apr 2027 | B9: Title 2 — Nature and Animals | C9: Lowest cultural risk, strongest proven artwork | D9: ≥20% of flagship buyers buy within 8 weeks, no discount | E9: Illustration commission
A10: Jul 2027 | B10: Activity kit | C10: The only SKU whose contribution carries a real CAC | E10: SASO/SABER for pencils — settle BEFORE scheduling
A11: Sep 2027 | B11: Ages 3-5 edition | C11: Unlocks the younger sibling | E11: —
A12: Q4 2027 | B12: Title 3 + second capsule | C12: Cadence of two titles a year | E12: —
A13: 2028 | B13: Ages 9-12, titles 4-5, educator pilot | C13: Extends lifetime rather than finding new customers | D13: Repeat rate >40% sustained | E13: Procurement cycles are slow
A14: 2029 | B14: Subscription | C14: Solves acquisition permanently | E14: Only above ~40% repeat, or it is a churn machine
A16: The Apr 2027 gate is the real one. Everything before it reuses artwork you have already paid for; everything after it commits new illustration money. If the existing customer list will not buy a second title at full price, the range thesis is wrong and no amount of further range will fix it.
